geowrangler/__init__.py
geowrangler/_modidx.py
geowrangler/area_zonal_stats.py
geowrangler/dhs.py
geowrangler/distance_zonal_stats.py
geowrangler/grids.py
geowrangler/raster_process.py
geowrangler/raster_to_dataframe.py
geowrangler/raster_zonal_stats.py
geowrangler/spatialjoin_highest_intersection.py
geowrangler/tile_clustering.py
geowrangler/validation.py
geowrangler/vector_to_raster_mask.py
geowrangler/vector_zonal_stats.py
geowrangler/datasets/__init__.py
geowrangler/datasets/geofabrik.py
geowrangler/datasets/nightlights.py
geowrangler/datasets/ookla.py
geowrangler/datasets/utils.py
geowrangler/gridding_utils/__init__.py
geowrangler/gridding_utils/polygon_fill.py
geowrangler-0.5.1.dist-info/LICENSE
geowrangler-0.5.1.dist-info/METADATA
geowrangler-0.5.1.dist-info/WHEEL
geowrangler-0.5.1.dist-info/entry_points.txt
geowrangler-0.5.1.dist-info/top_level.txt
geowrangler-0.5.1.dist-info/RECORD
