Metadata-Version: 2.1
Name: geowrangler
Version: 0.5.1
Summary: 🌏 A python package for wrangling geospatial datasets
Home-page: https://github.com/thinkingmachines/geowrangler
Author: Thinking Machines Data Sciences Inc.
Author-email: geowrangler@thinkingmachin.es
License: MIT License
Keywords: nbdev jupyter notebook python
Classifier: Development Status :: 4 - Beta
Classifier: Intended Audience :: Developers
Classifier: Natural Language :: English
Classifier: Programming Language :: Python :: 3.8
Classifier: Programming Language :: Python :: 3.9
Classifier: Programming Language :: Python :: 3.10
Classifier: License :: OSI Approved :: MIT License
Requires-Python: >=3.8
License-File: LICENSE
Requires-Dist: fastcore
Requires-Dist: pandas
Requires-Dist: numpy
Requires-Dist: geopandas >=1.0
Requires-Dist: fastprogress
Requires-Dist: h3
Requires-Dist: morecantile
Requires-Dist: loguru
Requires-Dist: rasterstats
Requires-Dist: scikit-learn
Requires-Dist: requests
Requires-Dist: pyarrow
Requires-Dist: exactextract
Requires-Dist: polars
Provides-Extra: dev
Requires-Dist: nbdev ; extra == 'dev'
Requires-Dist: jupyterlab ; extra == 'dev'
Requires-Dist: matplotlib ; extra == 'dev'
Requires-Dist: nbdime ; extra == 'dev'
Requires-Dist: ipytest ; extra == 'dev'
Requires-Dist: branca ; extra == 'dev'
Requires-Dist: folium ; extra == 'dev'
Requires-Dist: mapclassify ; extra == 'dev'
Requires-Dist: pytest ; extra == 'dev'
Requires-Dist: pytest-mock ; extra == 'dev'
Requires-Dist: pytest-cov ; extra == 'dev'
Requires-Dist: pytest-xdist ; extra == 'dev'
Requires-Dist: black[jupyter] ; extra == 'dev'
Requires-Dist: twine ; extra == 'dev'
